cs/__init__.py
cs/__main__.py
cs/_async.py
cs/client.py
cs/version.py
cs-3.4.0.dist-info/licenses/LICENSE
cs-3.4.0.dist-info/METADATA
cs-3.4.0.dist-info/WHEEL
cs-3.4.0.dist-info/entry_points.txt
cs-3.4.0.dist-info/top_level.txt
cs-3.4.0.dist-info/RECORD
