Metadata-Version: 2.4
Name: cs
Version: 3.4.0
Summary: A simple yet powerful CloudStack API client for Python and the command-line.
Home-page: https://github.com/ngine-io/cs
Author: Bruno Renié
License: BSD
Classifier: Intended Audience :: Developers
Classifier: Intended Audience :: System Administrators
Classifier: License :: OSI Approved :: BSD License
Classifier: Programming Language :: Python
Classifier: Programming Language :: Python :: 3
Classifier: Programming Language :: Python :: 3.9
Classifier: Programming Language :: Python :: 3.10
Classifier: Programming Language :: Python :: 3.11
Classifier: Programming Language :: Python :: 3.12
Classifier: Programming Language :: Python :: 3.13
License-File: LICENSE
Requires-Dist: pytz
Requires-Dist: requests
Provides-Extra: async
Requires-Dist: aiohttp; extra == "async"
Provides-Extra: highlight
Requires-Dist: pygments; extra == "highlight"
Dynamic: license-file
